<?xml version="1.0" encoding="UTF-8"?>
<objects serializationModel="Studio.01.09.00">
    <object class="Event" id="{ac9b2a54-37d3-4885-bb14-2f2fd6e5c1ed}">
        <property name="name">
            <value>water</value>
        </property>
        <property name="outputFormat">
            <value>2</value>
        </property>
        <relationship name="folder">
            <destination>{b46089d6-2e77-402f-9c0b-f60012b7d23b}</destination>
        </relationship>
        <relationship name="mixer">
            <destination>{b2a588d6-5848-40ba-a295-c03ac5b96c4a}</destination>
        </relationship>
        <relationship name="masterTrack">
            <destination>{11131301-9143-419d-86b0-398de3f43079}</destination>
        </relationship>
        <relationship name="mixerInput">
            <destination>{0b9add49-3918-4d41-a0c8-11f27dbf7515}</destination>
        </relationship>
        <relationship name="automatableProperties">
            <destination>{5c855ffc-85e8-4b40-8188-7c2d95528c43}</destination>
        </relationship>
        <relationship name="markerTracks">
            <destination>{11112776-99fc-4c12-a029-b693f814f8dd}</destination>
        </relationship>
        <relationship name="groupTracks">
            <destination>{467fbe4f-5e50-415f-91c4-df6310ccc467}</destination>
        </relationship>
        <relationship name="timeline">
            <destination>{0e641fe8-1f1a-42d5-9d05-cee577589f56}</destination>
        </relationship>
        <relationship name="banks">
            <destination>{2a1a2bc3-1e78-4c94-934a-a5980cf8f9e9}</destination>
        </relationship>
    </object>
    <object class="EventMixer" id="{b2a588d6-5848-40ba-a295-c03ac5b96c4a}">
        <relationship name="masterBus">
            <destination>{e896e855-807e-4457-8942-eddca501a42b}</destination>
        </relationship>
    </object>
    <object class="MasterTrack" id="{11131301-9143-419d-86b0-398de3f43079}">
        <relationship name="mixerGroup">
            <destination>{e896e855-807e-4457-8942-eddca501a42b}</destination>
        </relationship>
    </object>
    <object class="MixerInput" id="{0b9add49-3918-4d41-a0c8-11f27dbf7515}">
        <relationship name="effectChain">
            <destination>{5906c18b-d8b9-4ed5-9151-0e32f98e9e63}</destination>
        </relationship>
        <relationship name="panner">
            <destination>{69349481-abec-4e9b-b283-bf0fab0b55db}</destination>
        </relationship>
        <relationship name="output">
            <destination>{fb5b6733-ce87-4bc8-a1c9-bcbb4b6525c7}</destination>
        </relationship>
    </object>
    <object class="EventAutomatableProperties" id="{5c855ffc-85e8-4b40-8188-7c2d95528c43}"/>
    <object class="MarkerTrack" id="{11112776-99fc-4c12-a029-b693f814f8dd}"/>
    <object class="GroupTrack" id="{467fbe4f-5e50-415f-91c4-df6310ccc467}">
        <relationship name="modules">
            <destination>{232047a0-1a80-4fc4-8262-1963daee398b}</destination>
        </relationship>
        <relationship name="mixerGroup">
            <destination>{ea18dc8f-de63-417c-a393-f64b7c354162}</destination>
        </relationship>
    </object>
    <object class="Timeline" id="{0e641fe8-1f1a-42d5-9d05-cee577589f56}">
        <relationship name="modules">
            <destination>{232047a0-1a80-4fc4-8262-1963daee398b}</destination>
        </relationship>
        <relationship name="markers">
            <destination>{cad13eaf-523f-45f0-b53b-a12b7cdd5efe}</destination>
        </relationship>
    </object>
    <object class="EventMixerMaster" id="{e896e855-807e-4457-8942-eddca501a42b}">
        <relationship name="effectChain">
            <destination>{2ab8fc7b-6929-425c-a409-2c6c0bb3b790}</destination>
        </relationship>
        <relationship name="panner">
            <destination>{eb9cbea8-b64c-4f05-a976-2b267ebf33fb}</destination>
        </relationship>
        <relationship name="mixer">
            <destination>{b2a588d6-5848-40ba-a295-c03ac5b96c4a}</destination>
        </relationship>
    </object>
    <object class="MixerBusEffectChain" id="{5906c18b-d8b9-4ed5-9151-0e32f98e9e63}">
        <relationship name="effects">
            <destination>{a65222d3-255f-476a-95ff-30d9e4e8cf8f}</destination>
        </relationship>
    </object>
    <object class="MixerBusPanner" id="{69349481-abec-4e9b-b283-bf0fab0b55db}"/>
    <object class="SingleSound" id="{232047a0-1a80-4fc4-8262-1963daee398b}">
        <property name="length">
            <value>6.5</value>
        </property>
        <relationship name="audioFile">
            <destination>{cece2e37-6ab0-4557-9d20-c07c15271d6d}</destination>
        </relationship>
    </object>
    <object class="EventMixerGroup" id="{ea18dc8f-de63-417c-a393-f64b7c354162}">
        <property name="volume">
            <value>-18.5</value>
        </property>
        <property name="name">
            <value>Audio 1</value>
        </property>
        <relationship name="effectChain">
            <destination>{3158dd45-4139-439f-954e-8fd6288178ff}</destination>
        </relationship>
        <relationship name="panner">
            <destination>{5ef75927-facd-4386-8876-11897a2b2387}</destination>
        </relationship>
        <relationship name="output">
            <destination>{e896e855-807e-4457-8942-eddca501a42b}</destination>
        </relationship>
    </object>
    <object class="LoopRegion" id="{cad13eaf-523f-45f0-b53b-a12b7cdd5efe}">
        <property name="position">
            <value>0</value>
        </property>
        <property name="length">
            <value>6.5</value>
        </property>
        <relationship name="timeline">
            <destination>{0e641fe8-1f1a-42d5-9d05-cee577589f56}</destination>
        </relationship>
        <relationship name="markerTrack">
            <destination>{11112776-99fc-4c12-a029-b693f814f8dd}</destination>
        </relationship>
    </object>
    <object class="MixerBusEffectChain" id="{2ab8fc7b-6929-425c-a409-2c6c0bb3b790}">
        <relationship name="effects">
            <destination>{619b7f39-3e82-49a1-89bb-4820f184f3ca}</destination>
            <destination>{b3f71366-a4f1-4396-99ef-70af24cf6257}</destination>
        </relationship>
    </object>
    <object class="MixerBusPanner" id="{eb9cbea8-b64c-4f05-a976-2b267ebf33fb}"/>
    <object class="MixerBusFader" id="{a65222d3-255f-476a-95ff-30d9e4e8cf8f}"/>
    <object class="MixerBusEffectChain" id="{3158dd45-4139-439f-954e-8fd6288178ff}">
        <relationship name="effects">
            <destination>{aa66630d-0d91-4f00-85f0-5444a41729ea}</destination>
        </relationship>
    </object>
    <object class="MixerBusPanner" id="{5ef75927-facd-4386-8876-11897a2b2387}"/>
    <object class="MixerBusFader" id="{619b7f39-3e82-49a1-89bb-4820f184f3ca}"/>
    <object class="SpatialiserEffect" id="{b3f71366-a4f1-4396-99ef-70af24cf6257}"/>
    <object class="MixerBusFader" id="{aa66630d-0d91-4f00-85f0-5444a41729ea}"/>
</objects>
